{
  "image_name": "01967.jpg",
  "mean_iou": 0.6357087825719573,
  "single_iou": [
    [
      "00",
      0.7960871503340401
    ],
    [
      "01",
      0.6472458548547233
    ],
    [
      "02",
      0.9130108073228196
    ],
    [
      "03",
      0.7919904849605676
    ],
    [
      "04",
      0.0
    ],
    [
      "05",
      0.6659183979595933
    ]
  ],
  "yolo_labels": [
    {
      "class_id": 1,
      "class_name": "shelf",
      "coordinates": [
        0.0,
        0.424543,
        0.891107,
        0.220435,
        0.898893,
        0.239565,
        0.007787,
        0.443673
      ]
    },
    {
      "class_id": 1,
      "class_name": "shelf",
      "coordinates": [
        0.0,
        0.594706,
        0.862813,
        0.370275,
        0.867187,
        0.379725,
        0.004373,
        0.604156
      ]
    },
    {
      "class_id": 1,
      "class_name": "shelf",
      "coordinates": [
        0.0,
        0.739138,
        0.8448,
        0.47079,
        0.8552,
        0.48921,
        0.0104,
        0.757558
      ]
    },
    {
      "class_id": 1,
      "class_name": "shelf",
      "coordinates": [
        0.061833,
        0.255285,
        0.906833,
        0.100285,
        0.913167,
        0.119715,
        0.068167,
        0.274715
      ]
    },
    {
      "class_id": 1,
      "class_name": "shelf",
      "coordinates": [
        0.0,
        0.08,
        0.78,
        -0.0,
        0.78,
        -0.0,
        0.0,
        0.08
      ]
    },
    {
      "class_id": 1,
      "class_name": "shelf",
      "coordinates": [
        0.0,
        0.198598,
        0.025507,
        0.19131,
        0.044493,
        0.22869,
        0.018987,
        0.235978
      ]
    },
    {
      "class_id": 0,
      "class_name": "shelf-space",
      "coordinates": [
        0.0,
        0.63749,
        0.84822,
        0.39234,
        0.88178,
        0.45766,
        0.03356,
        0.70281
      ]
    },
    {
      "class_id": 0,
      "class_name": "shelf-space",
      "coordinates": [
        0.0,
        0.456825,
        0.86496,
        0.243015,
        0.91504,
        0.356985,
        0.05008,
        0.570795
      ]
    },
    {
      "class_id": 0,
      "class_name": "shelf-space",
      "coordinates": [
        0.0,
        0.283703,
        0.8959,
        0.12126,
        0.9241,
        0.20874,
        0.0282,
        0.371183
      ]
    },
    {
      "class_id": 0,
      "class_name": "shelf-space",
      "coordinates": [
        0.0,
        0.104491,
        0.921067,
        0.0005,
        0.938933,
        0.0895,
        0.017867,
        0.193491
      ]
    },
    {
      "class_id": 0,
      "class_name": "shelf-space",
      "coordinates": [
        0.0,
        0.0,
        0.245,
        0.0,
        0.245,
        0.06,
        0.0,
        0.06
      ]
    }
  ],
  "segmentation_labels": [
    {
      "probability": 100,
      "type": "polygon",
      "className": "shelf",
      "points": [
        0,
        840,
        0,
        900,
        1350,
        480,
        1335,
        440
      ],
      "groupId": 0,
      "pointLabels": {},
      "attributes": [],
      "error": null,
      "locked": false,
      "creationType": "Preannotation",
      "classId": 1981314
    },
    {
      "probability": 100,
      "type": "polygon",
      "className": "shelf",
      "points": [
        0,
        1180,
        0,
        1220,
        1305,
        760,
        1290,
        740
      ],
      "groupId": 0,
      "pointLabels": {},
      "attributes": [],
      "error": null,
      "locked": false,
      "creationType": "Preannotation",
      "classId": 1981314
    },
    {
      "probability": 100,
      "type": "polygon",
      "className": "shelf",
      "points": [
        0,
        1480,
        0,
        1520,
        1275,
        980,
        1275,
        940
      ],
      "groupId": 0,
      "pointLabels": {},
      "attributes": [],
      "error": null,
      "locked": false,
      "creationType": "Preannotation",
      "classId": 1981314
    },
    {
      "probability": 100,
      "type": "polygon",
      "className": "shelf",
      "points": [
        90,
        500,
        105,
        560,
        1365,
        240,
        1365,
        200
      ],
      "groupId": 0,
      "pointLabels": {},
      "attributes": [],
      "error": null,
      "locked": false,
      "creationType": "Preannotation",
      "classId": 1981314
    },
    {
      "probability": 100,
      "type": "polygon",
      "className": "shelf",
      "points": [
        0,
        120,
        0,
        200,
        1170,
        0,
        795,
        0
      ],
      "groupId": 0,
      "pointLabels": {},
      "attributes": [],
      "error": null,
      "locked": false,
      "creationType": "Preannotation",
      "classId": 1981314
    },
    {
      "probability": 100,
      "type": "polygon",
      "className": "shelf",
      "points": [
        0,
        400,
        0,
        480,
        60,
        460,
        45,
        380
      ],
      "groupId": 0,
      "pointLabels": {},
      "attributes": [],
      "error": null,
      "locked": false,
      "creationType": "Preannotation",
      "classId": 1981314
    },
    {
      "probability": 100,
      "type": "polygon",
      "className": "shelf-space",
      "points": [
        0,
        1240,
        0,
        1460,
        1275,
        920,
        1320,
        780
      ],
      "groupId": 0,
      "pointLabels": {},
      "attributes": [],
      "error": null,
      "locked": false,
      "creationType": "Preannotation",
      "classId": 1981315
    },
    {
      "probability": 100,
      "type": "polygon",
      "className": "shelf-space",
      "points": [
        0,
        900,
        0,
        1180,
        1320,
        720,
        1350,
        480
      ],
      "groupId": 0,
      "pointLabels": {},
      "attributes": [],
      "error": null,
      "locked": false,
      "creationType": "Preannotation",
      "classId": 1981315
    },
    {
      "probability": 100,
      "type": "polygon",
      "className": "shelf-space",
      "points": [
        0,
        480,
        0,
        840,
        1350,
        420,
        1380,
        240,
        105,
        560,
        75,
        460
      ],
      "groupId": 0,
      "pointLabels": {},
      "attributes": [],
      "error": null,
      "locked": false,
      "creationType": "Preannotation",
      "classId": 1981315
    },
    {
      "probability": 100,
      "type": "polygon",
      "className": "shelf-space",
      "points": [
        0,
        200,
        0,
        400,
        60,
        380,
        75,
        500,
        1395,
        180,
        1395,
        0,
        1200,
        0
      ],
      "groupId": 0,
      "pointLabels": {},
      "attributes": [],
      "error": null,
      "locked": false,
      "creationType": "Preannotation",
      "classId": 1981315
    },
    {
      "probability": 100,
      "type": "polygon",
      "className": "shelf-space",
      "points": [
        0,
        0,
        0,
        120,
        735,
        0
      ],
      "groupId": 0,
      "pointLabels": {},
      "attributes": [],
      "error": null,
      "locked": false,
      "creationType": "Preannotation",
      "classId": 1981315
    }
  ],
  "metadata": {
    "source_json": "shelf_analysis_results\\iou_scores.json",
    "total_instances": 6,
    "rank": 944
  }
}