{
  "image_name": "04624.jpg",
  "mean_iou": 0.6174497712893922,
  "single_iou": [
    [
      "00",
      0.9810240156488512
    ],
    [
      "01",
      0.6660958517188141
    ],
    [
      "02",
      0.4907747918389112
    ],
    [
      "03",
      0.6455923164181102
    ],
    [
      "04",
      0.666262740410727
    ],
    [
      "05",
      0.0
    ],
    [
      "06",
      0.9250958510702654
    ],
    [
      "07",
      0.6523134623043729
    ],
    [
      "08",
      0.0
    ],
    [
      "09",
      0.811500677126253
    ],
    [
      "10",
      0.6290994392994096
    ],
    [
      "11",
      0.8161555463559773
    ],
    [
      "12",
      0.7429323345704059
    ]
  ],
  "yolo_labels": [
    {
      "class_id": 1,
      "class_name": "shelf",
      "coordinates": [
        0.00452,
        0.120437,
        0.93226,
        0.240145,
        0.92774,
        0.259855,
        0.0,
        0.140147
      ]
    },
    {
      "class_id": 1,
      "class_name": "shelf",
      "coordinates": [
        9.3e-05,
        0.315,
        0.925047,
        0.32,
        0.924953,
        0.33,
        0.0,
        0.325
      ]
    },
    {
      "class_id": 1,
      "class_name": "shelf",
      "coordinates": [
        0.0,
        0.499947,
        0.924047,
        0.40005,
        0.925953,
        0.40995,
        0.001907,
        0.509847
      ]
    },
    {
      "class_id": 1,
      "class_name": "shelf",
      "coordinates": [
        0.0,
        0.694766,
        0.923027,
        0.480225,
        0.926973,
        0.489775,
        0.003947,
        0.704316
      ]
    },
    {
      "class_id": 1,
      "class_name": "shelf",
      "coordinates": [
        0.186993,
        0.86554,
        0.911993,
        0.59054,
        0.918007,
        0.59946,
        0.193007,
        0.87446
      ]
    },
    {
      "class_id": 1,
      "class_name": "shelf",
      "coordinates": [
        0.31,
        0.96,
        0.915,
        0.67,
        0.915,
        0.67,
        0.31,
        0.96
      ]
    },
    {
      "class_id": 1,
      "class_name": "shelf",
      "coordinates": [
        0.0,
        0.898995,
        0.139433,
        0.850915,
        0.150567,
        0.869085,
        0.011133,
        0.917165
      ]
    },
    {
      "class_id": 1,
      "class_name": "shelf",
      "coordinates": [
        0.9837,
        0.31084,
        1.0,
        0.31899,
        0.9926,
        0.32731,
        0.9763,
        0.31916
      ]
    },
    {
      "class_id": 1,
      "class_name": "shelf",
      "coordinates": [
        0.97,
        0.39,
        1.0,
        0.39,
        1.0,
        0.39,
        0.97,
        0.39
      ]
    },
    {
      "class_id": 1,
      "class_name": "shelf",
      "coordinates": [
        0.967293,
        0.47043,
        0.994587,
        0.461332,
        1.0,
        0.470472,
        0.972707,
        0.47957
      ]
    },
    {
      "class_id": 1,
      "class_name": "shelf",
      "coordinates": [
        0.965573,
        0.541265,
        0.991147,
        0.524216,
        1.0,
        0.531686,
        0.974427,
        0.548735
      ]
    },
    {
      "class_id": 1,
      "class_name": "shelf",
      "coordinates": [
        0.96096,
        0.611025,
        0.99192,
        0.593334,
        1.0,
        0.601284,
        0.96904,
        0.618975
      ]
    },
    {
      "class_id": 1,
      "class_name": "shelf",
      "coordinates": [
        0.95494,
        0.696745,
        0.98988,
        0.666173,
        1.0,
        0.672682,
        0.96506,
        0.703255
      ]
    },
    {
      "class_id": 0,
      "class_name": "shelf-space",
      "coordinates": [
        0.007467,
        0.195392,
        0.928733,
        0.26013,
        0.921267,
        0.31987,
        0.0,
        0.255132
      ]
    },
    {
      "class_id": 0,
      "class_name": "shelf-space",
      "coordinates": [
        0.0,
        0.374928,
        0.92198,
        0.330075,
        0.92802,
        0.399925,
        0.00604,
        0.444778
      ]
    },
    {
      "class_id": 0,
      "class_name": "shelf-space",
      "coordinates": [
        0.0,
        0.569081,
        0.914513,
        0.410895,
        0.935487,
        0.479105,
        0.020973,
        0.637291
      ]
    },
    {
      "class_id": 0,
      "class_name": "shelf-space",
      "coordinates": [
        0.149627,
        0.723765,
        0.894627,
        0.493765,
        0.945373,
        0.586235,
        0.200373,
        0.816235
      ]
    },
    {
      "class_id": 0,
      "class_name": "shelf-space",
      "coordinates": [
        0.0,
        0.719609,
        0.087693,
        0.695055,
        0.162307,
        0.844945,
        0.074613,
        0.869499
      ]
    },
    {
      "class_id": 0,
      "class_name": "shelf-space",
      "coordinates": [
        0.182387,
        0.889385,
        0.892387,
        0.594385,
        0.937613,
        0.655615,
        0.227613,
        0.950615
      ]
    },
    {
      "class_id": 0,
      "class_name": "shelf-space",
      "coordinates": [
        0.0,
        0.919643,
        0.170013,
        0.895355,
        0.179987,
        0.934645,
        0.009973,
        0.958933
      ]
    },
    {
      "class_id": 0,
      "class_name": "shelf-space",
      "coordinates": [
        0.934393,
        0.631955,
        0.948787,
        0.622959,
        1.0,
        0.669049,
        0.985607,
        0.678045
      ]
    },
    {
      "class_id": 0,
      "class_name": "shelf-space",
      "coordinates": [
        0.94076,
        0.556135,
        0.95152,
        0.549986,
        1.0,
        0.597716,
        0.98924,
        0.603865
      ]
    },
    {
      "class_id": 0,
      "class_name": "shelf-space",
      "coordinates": [
        0.951507,
        0.4892,
        0.963013,
        0.483447,
        1.0,
        0.525047,
        0.988493,
        0.5308
      ]
    },
    {
      "class_id": 0,
      "class_name": "shelf-space",
      "coordinates": [
        0.959873,
        0.395835,
        0.979747,
        0.392523,
        1.0,
        0.460853,
        0.980127,
        0.464165
      ]
    },
    {
      "class_id": 0,
      "class_name": "shelf-space",
      "coordinates": [
        0.966413,
        0.335845,
        0.982827,
        0.332562,
        1.0,
        0.380872,
        0.983587,
        0.384155
      ]
    },
    {
      "class_id": 0,
      "class_name": "shelf-space",
      "coordinates": [
        0.025333,
        0.007749,
        0.942667,
        0.14091,
        0.917333,
        0.23909,
        0.0,
        0.105929
      ]
    }
  ],
  "segmentation_labels": [
    {
      "probability": 100,
      "type": "polygon",
      "className": "shelf",
      "points": [
        1395,
        480,
        0,
        240,
        0,
        280,
        1395,
        520
      ],
      "groupId": 0,
      "pointLabels": {},
      "attributes": [],
      "error": null,
      "locked": false,
      "creationType": "Preannotation",
      "classId": 1981314
    },
    {
      "probability": 100,
      "type": "polygon",
      "className": "shelf",
      "points": [
        1380,
        640,
        0,
        620,
        0,
        660,
        1395,
        660
      ],
      "groupId": 0,
      "pointLabels": {},
      "attributes": [],
      "error": null,
      "locked": false,
      "creationType": "Preannotation",
      "classId": 1981314
    },
    {
      "probability": 100,
      "type": "polygon",
      "className": "shelf",
      "points": [
        1380,
        800,
        0,
        980,
        0,
        1040,
        1395,
        820
      ],
      "groupId": 0,
      "pointLabels": {},
      "attributes": [],
      "error": null,
      "locked": false,
      "creationType": "Preannotation",
      "classId": 1981314
    },
    {
      "probability": 100,
      "type": "polygon",
      "className": "shelf",
      "points": [
        1380,
        960,
        0,
        1380,
        0,
        1420,
        1395,
        980
      ],
      "groupId": 0,
      "pointLabels": {},
      "attributes": [],
      "error": null,
      "locked": false,
      "creationType": "Preannotation",
      "classId": 1981314
    },
    {
      "probability": 100,
      "type": "polygon",
      "className": "shelf",
      "points": [
        1365,
        1180,
        285,
        1720,
        285,
        1760,
        1380,
        1200
      ],
      "groupId": 0,
      "pointLabels": {},
      "attributes": [],
      "error": null,
      "locked": false,
      "creationType": "Preannotation",
      "classId": 1981314
    },
    {
      "probability": 100,
      "type": "polygon",
      "className": "shelf",
      "points": [
        1365,
        1320,
        465,
        1920,
        525,
        1920,
        1380,
        1360
      ],
      "groupId": 0,
      "pointLabels": {},
      "attributes": [],
      "error": null,
      "locked": false,
      "creationType": "Preannotation",
      "classId": 1981314
    },
    {
      "probability": 100,
      "type": "polygon",
      "className": "shelf",
      "points": [
        210,
        1700,
        0,
        1800,
        0,
        1840,
        225,
        1740
      ],
      "groupId": 0,
      "pointLabels": {},
      "attributes": [],
      "error": null,
      "locked": false,
      "creationType": "Preannotation",
      "classId": 1981314
    },
    {
      "probability": 100,
      "type": "polygon",
      "className": "shelf",
      "points": [
        1470,
        620,
        1470,
        640,
        1500,
        660,
        1500,
        640
      ],
      "groupId": 0,
      "pointLabels": {},
      "attributes": [],
      "error": null,
      "locked": false,
      "creationType": "Preannotation",
      "classId": 1981314
    },
    {
      "probability": 100,
      "type": "polygon",
      "className": "shelf",
      "points": [
        1455,
        780,
        1455,
        780,
        1500,
        780,
        1500,
        780
      ],
      "groupId": 0,
      "pointLabels": {},
      "attributes": [],
      "error": null,
      "locked": false,
      "creationType": "Preannotation",
      "classId": 1981314
    },
    {
      "probability": 100,
      "type": "polygon",
      "className": "shelf",
      "points": [
        1455,
        940,
        1455,
        960,
        1500,
        940,
        1500,
        920
      ],
      "groupId": 0,
      "pointLabels": {},
      "attributes": [],
      "error": null,
      "locked": false,
      "creationType": "Preannotation",
      "classId": 1981314
    },
    {
      "probability": 100,
      "type": "polygon",
      "className": "shelf",
      "points": [
        1455,
        1080,
        1455,
        1100,
        1500,
        1060,
        1500,
        1040
      ],
      "groupId": 0,
      "pointLabels": {},
      "attributes": [],
      "error": null,
      "locked": false,
      "creationType": "Preannotation",
      "classId": 1981314
    },
    {
      "probability": 100,
      "type": "polygon",
      "className": "shelf",
      "points": [
        1440,
        1220,
        1455,
        1240,
        1500,
        1200,
        1500,
        1180
      ],
      "groupId": 0,
      "pointLabels": {},
      "attributes": [],
      "error": null,
      "locked": false,
      "creationType": "Preannotation",
      "classId": 1981314
    },
    {
      "probability": 100,
      "type": "polygon",
      "className": "shelf",
      "points": [
        1440,
        1380,
        1440,
        1420,
        1500,
        1340,
        1500,
        1320
      ],
      "groupId": 0,
      "pointLabels": {},
      "attributes": [],
      "error": null,
      "locked": false,
      "creationType": "Preannotation",
      "classId": 1981314
    },
    {
      "probability": 100,
      "type": "polygon",
      "className": "shelf-space",
      "points": [
        1395,
        520,
        0,
        280,
        0,
        620,
        1380,
        640
      ],
      "groupId": 0,
      "pointLabels": {},
      "attributes": [],
      "error": null,
      "locked": false,
      "creationType": "Preannotation",
      "classId": 1981315
    },
    {
      "probability": 100,
      "type": "polygon",
      "className": "shelf-space",
      "points": [
        1395,
        660,
        0,
        660,
        0,
        980,
        1380,
        800
      ],
      "groupId": 0,
      "pointLabels": {},
      "attributes": [],
      "error": null,
      "locked": false,
      "creationType": "Preannotation",
      "classId": 1981315
    },
    {
      "probability": 100,
      "type": "polygon",
      "className": "shelf-space",
      "points": [
        1395,
        820,
        0,
        1040,
        0,
        1380,
        1380,
        960
      ],
      "groupId": 0,
      "pointLabels": {},
      "attributes": [],
      "error": null,
      "locked": false,
      "creationType": "Preannotation",
      "classId": 1981315
    },
    {
      "probability": 100,
      "type": "polygon",
      "className": "shelf-space",
      "points": [
        285,
        1720,
        240,
        1360,
        1395,
        980,
        1365,
        1180
      ],
      "groupId": 0,
      "pointLabels": {},
      "attributes": [],
      "error": null,
      "locked": false,
      "creationType": "Preannotation",
      "classId": 1981315
    },
    {
      "probability": 100,
      "type": "polygon",
      "className": "shelf-space",
      "points": [
        195,
        1700,
        180,
        1380,
        0,
        1420,
        0,
        1800
      ],
      "groupId": 0,
      "pointLabels": {},
      "attributes": [],
      "error": null,
      "locked": false,
      "creationType": "Preannotation",
      "classId": 1981315
    },
    {
      "probability": 100,
      "type": "polygon",
      "className": "shelf-space",
      "points": [
        1380,
        1180,
        285,
        1760,
        330,
        1920,
        465,
        1920,
        1365,
        1320
      ],
      "groupId": 0,
      "pointLabels": {},
      "attributes": [],
      "error": null,
      "locked": false,
      "creationType": "Preannotation",
      "classId": 1981315
    },
    {
      "probability": 100,
      "type": "polygon",
      "className": "shelf-space",
      "points": [
        225,
        1740,
        0,
        1840,
        0,
        1920,
        300,
        1920
      ],
      "groupId": 0,
      "pointLabels": {},
      "attributes": [],
      "error": null,
      "locked": false,
      "creationType": "Preannotation",
      "classId": 1981315
    },
    {
      "probability": 100,
      "type": "polygon",
      "className": "shelf-space",
      "points": [
        1455,
        1240,
        1425,
        1380,
        1500,
        1320,
        1500,
        1200
      ],
      "groupId": 0,
      "pointLabels": {},
      "attributes": [],
      "error": null,
      "locked": false,
      "creationType": "Preannotation",
      "classId": 1981315
    },
    {
      "probability": 100,
      "type": "polygon",
      "className": "shelf-space",
      "points": [
        1455,
        1100,
        1440,
        1220,
        1500,
        1180,
        1500,
        1060
      ],
      "groupId": 0,
      "pointLabels": {},
      "attributes": [],
      "error": null,
      "locked": false,
      "creationType": "Preannotation",
      "classId": 1981315
    },
    {
      "probability": 100,
      "type": "polygon",
      "className": "shelf-space",
      "points": [
        1455,
        960,
        1455,
        1080,
        1500,
        1040,
        1500,
        940
      ],
      "groupId": 0,
      "pointLabels": {},
      "attributes": [],
      "error": null,
      "locked": false,
      "creationType": "Preannotation",
      "classId": 1981315
    },
    {
      "probability": 100,
      "type": "polygon",
      "className": "shelf-space",
      "points": [
        1455,
        940,
        1455,
        780,
        1500,
        780,
        1500,
        920
      ],
      "groupId": 0,
      "pointLabels": {},
      "attributes": [],
      "error": null,
      "locked": false,
      "creationType": "Preannotation",
      "classId": 1981315
    },
    {
      "probability": 100,
      "type": "polygon",
      "className": "shelf-space",
      "points": [
        1455,
        780,
        1470,
        660,
        1500,
        660,
        1500,
        760
      ],
      "groupId": 0,
      "pointLabels": {},
      "attributes": [],
      "error": null,
      "locked": false,
      "creationType": "Preannotation",
      "classId": 1981315
    },
    {
      "probability": 100,
      "type": "polygon",
      "className": "shelf-space",
      "points": [
        0,
        0,
        0,
        220,
        1395,
        480,
        1395,
        280,
        225,
        20
      ],
      "groupId": 0,
      "pointLabels": {},
      "attributes": [],
      "error": null,
      "locked": false,
      "creationType": "Preannotation",
      "classId": 1981315
    }
  ],
  "metadata": {
    "source_json": "shelf_analysis_results\\iou_scores.json",
    "total_instances": 13,
    "rank": 775
  }
}