{
  "image_name": "08749.jpg",
  "mean_iou": 0.530295047571823,
  "single_iou": [
    [
      "00",
      0.6851721676686237
    ],
    [
      "01",
      0.6642142051000466
    ],
    [
      "02",
      0.652388747998427
    ],
    [
      "03",
      0.0
    ],
    [
      "04",
      0.4966837144404039
    ],
    [
      "05",
      0.6592875065432634
    ],
    [
      "06",
      0.5543189912519972
    ]
  ],
  "yolo_labels": [
    {
      "class_id": 1,
      "class_name": "shelf",
      "coordinates": [
        0.00168,
        0.14512,
        0.99584,
        0.24004,
        0.99416,
        0.24996,
        0.0,
        0.15504
      ]
    },
    {
      "class_id": 1,
      "class_name": "shelf",
      "coordinates": [
        0.0,
        0.305,
        0.994953,
        0.3,
        0.995047,
        0.31,
        9.3e-05,
        0.315
      ]
    },
    {
      "class_id": 1,
      "class_name": "shelf",
      "coordinates": [
        0.0,
        0.454966,
        0.994247,
        0.37003,
        0.995753,
        0.37997,
        0.001507,
        0.464906
      ]
    },
    {
      "class_id": 1,
      "class_name": "shelf",
      "coordinates": [
        0.005,
        0.605,
        1.0,
        0.43,
        1.0,
        0.43,
        0.005,
        0.605
      ]
    },
    {
      "class_id": 1,
      "class_name": "shelf",
      "coordinates": [
        0.0,
        0.729727,
        0.99288,
        0.48026,
        0.99712,
        0.48974,
        0.00424,
        0.739207
      ]
    },
    {
      "class_id": 1,
      "class_name": "shelf",
      "coordinates": [
        0.0,
        0.86452,
        0.992267,
        0.53044,
        0.997733,
        0.53956,
        0.005467,
        0.87364
      ]
    },
    {
      "class_id": 1,
      "class_name": "shelf",
      "coordinates": [
        0.0,
        0.959395,
        0.993973,
        0.581685,
        1.0,
        0.590605,
        0.006027,
        0.968315
      ]
    },
    {
      "class_id": 0,
      "class_name": "shelf-space",
      "coordinates": [
        0.009787,
        0.061025,
        1.0,
        0.199655,
        0.990213,
        0.238975,
        0.0,
        0.100345
      ]
    },
    {
      "class_id": 0,
      "class_name": "shelf-space",
      "coordinates": [
        0.0032,
        0.215107,
        1.0,
        0.259963,
        0.9968,
        0.299893,
        0.0,
        0.255037
      ]
    },
    {
      "class_id": 0,
      "class_name": "shelf-space",
      "coordinates": [
        0.0,
        0.369956,
        0.996453,
        0.320134,
        1.0,
        0.360044,
        0.003547,
        0.409866
      ]
    },
    {
      "class_id": 0,
      "class_name": "shelf-space",
      "coordinates": [
        0.0,
        0.514677,
        0.990547,
        0.380953,
        1.0,
        0.420323,
        0.009453,
        0.554047
      ]
    },
    {
      "class_id": 0,
      "class_name": "shelf-space",
      "coordinates": [
        0.0,
        0.645266,
        0.98524,
        0.432375,
        1.0,
        0.470815,
        0.01476,
        0.683706
      ]
    },
    {
      "class_id": 0,
      "class_name": "shelf-space",
      "coordinates": [
        0.0,
        0.788847,
        0.985147,
        0.493303,
        1.0,
        0.521153,
        0.014853,
        0.816697
      ]
    },
    {
      "class_id": 0,
      "class_name": "shelf-space",
      "coordinates": [
        0.0,
        0.910708,
        0.988413,
        0.553091,
        1.0,
        0.571101,
        0.011587,
        0.928718
      ]
    }
  ],
  "segmentation_labels": [
    {
      "probability": 100,
      "type": "polygon",
      "className": "shelf",
      "points": [
        1485,
        480,
        0,
        280,
        0,
        320,
        1500,
        500
      ],
      "groupId": 0,
      "pointLabels": {},
      "attributes": [],
      "error": null,
      "locked": false,
      "creationType": "Preannotation",
      "classId": 1981314
    },
    {
      "probability": 100,
      "type": "polygon",
      "className": "shelf",
      "points": [
        1485,
        600,
        0,
        600,
        0,
        640,
        1500,
        620
      ],
      "groupId": 0,
      "pointLabels": {},
      "attributes": [],
      "error": null,
      "locked": false,
      "creationType": "Preannotation",
      "classId": 1981314
    },
    {
      "probability": 100,
      "type": "polygon",
      "className": "shelf",
      "points": [
        1485,
        740,
        0,
        900,
        0,
        940,
        1500,
        760
      ],
      "groupId": 0,
      "pointLabels": {},
      "attributes": [],
      "error": null,
      "locked": false,
      "creationType": "Preannotation",
      "classId": 1981314
    },
    {
      "probability": 100,
      "type": "polygon",
      "className": "shelf",
      "points": [
        1485,
        860,
        0,
        1180,
        15,
        1240,
        1500,
        860
      ],
      "groupId": 0,
      "pointLabels": {},
      "attributes": [],
      "error": null,
      "locked": false,
      "creationType": "Preannotation",
      "classId": 1981314
    },
    {
      "probability": 100,
      "type": "polygon",
      "className": "shelf",
      "points": [
        1485,
        960,
        0,
        1440,
        0,
        1500,
        1500,
        980
      ],
      "groupId": 0,
      "pointLabels": {},
      "attributes": [],
      "error": null,
      "locked": false,
      "creationType": "Preannotation",
      "classId": 1981314
    },
    {
      "probability": 100,
      "type": "polygon",
      "className": "shelf",
      "points": [
        1485,
        1060,
        0,
        1720,
        0,
        1760,
        1500,
        1080
      ],
      "groupId": 0,
      "pointLabels": {},
      "attributes": [],
      "error": null,
      "locked": false,
      "creationType": "Preannotation",
      "classId": 1981314
    },
    {
      "probability": 100,
      "type": "polygon",
      "className": "shelf",
      "points": [
        1500,
        1160,
        0,
        1900,
        0,
        1960,
        1500,
        1180
      ],
      "groupId": 0,
      "pointLabels": {},
      "attributes": [],
      "error": null,
      "locked": false,
      "creationType": "Preannotation",
      "classId": 1981314
    },
    {
      "probability": 100,
      "type": "polygon",
      "className": "shelf-space",
      "points": [
        1500,
        400,
        0,
        40,
        0,
        280,
        1500,
        480
      ],
      "groupId": 0,
      "pointLabels": {},
      "attributes": [],
      "error": null,
      "locked": false,
      "creationType": "Preannotation",
      "classId": 1981315
    },
    {
      "probability": 100,
      "type": "polygon",
      "className": "shelf-space",
      "points": [
        1500,
        520,
        0,
        340,
        0,
        600,
        1500,
        600
      ],
      "groupId": 0,
      "pointLabels": {},
      "attributes": [],
      "error": null,
      "locked": false,
      "creationType": "Preannotation",
      "classId": 1981315
    },
    {
      "probability": 100,
      "type": "polygon",
      "className": "shelf-space",
      "points": [
        1500,
        640,
        0,
        660,
        0,
        900,
        1275,
        740,
        1500,
        720
      ],
      "groupId": 0,
      "pointLabels": {},
      "attributes": [],
      "error": null,
      "locked": false,
      "creationType": "Preannotation",
      "classId": 1981315
    },
    {
      "probability": 100,
      "type": "polygon",
      "className": "shelf-space",
      "points": [
        1500,
        760,
        0,
        960,
        0,
        1180,
        1500,
        840
      ],
      "groupId": 0,
      "pointLabels": {},
      "attributes": [],
      "error": null,
      "locked": false,
      "creationType": "Preannotation",
      "classId": 1981315
    },
    {
      "probability": 100,
      "type": "polygon",
      "className": "shelf-space",
      "points": [
        1500,
        860,
        0,
        1240,
        15,
        1420,
        1500,
        940
      ],
      "groupId": 0,
      "pointLabels": {},
      "attributes": [],
      "error": null,
      "locked": false,
      "creationType": "Preannotation",
      "classId": 1981315
    },
    {
      "probability": 100,
      "type": "polygon",
      "className": "shelf-space",
      "points": [
        1500,
        980,
        0,
        1500,
        0,
        1720,
        1200,
        1180,
        1500,
        1040
      ],
      "groupId": 0,
      "pointLabels": {},
      "attributes": [],
      "error": null,
      "locked": false,
      "creationType": "Preannotation",
      "classId": 1981315
    },
    {
      "probability": 100,
      "type": "polygon",
      "className": "shelf-space",
      "points": [
        1500,
        1100,
        15,
        1780,
        0,
        1900,
        1500,
        1140
      ],
      "groupId": 0,
      "pointLabels": {},
      "attributes": [],
      "error": null,
      "locked": false,
      "creationType": "Preannotation",
      "classId": 1981315
    }
  ],
  "metadata": {
    "source_json": "shelf_analysis_results\\iou_scores.json",
    "total_instances": 7,
    "rank": 326
  }
}